ibm_agent_analytics_common/__init__.py
ibm_agent_analytics_common/interfaces/__init__.py
ibm_agent_analytics_common/interfaces/action.py
ibm_agent_analytics_common/interfaces/annotations.py
ibm_agent_analytics_common/interfaces/elements.py
ibm_agent_analytics_common/interfaces/events.py
ibm_agent_analytics_common/interfaces/graph.py
ibm_agent_analytics_common/interfaces/issues.py
ibm_agent_analytics_common/interfaces/iunits.py
ibm_agent_analytics_common/interfaces/metric.py
ibm_agent_analytics_common/interfaces/recommendations.py
ibm_agent_analytics_common/interfaces/relatable_element.py
ibm_agent_analytics_common/interfaces/resources.py
ibm_agent_analytics_common/interfaces/runnable.py
ibm_agent_analytics_common/interfaces/task.py
ibm_agent_analytics_common-0.1.6.dist-info/licenses/LICENSE
ibm_agent_analytics_common-0.1.6.dist-info/METADATA
ibm_agent_analytics_common-0.1.6.dist-info/WHEEL
ibm_agent_analytics_common-0.1.6.dist-info/top_level.txt
ibm_agent_analytics_common-0.1.6.dist-info/RECORD
